gspread_pandas/__init__.py
gspread_pandas/_version.py
gspread_pandas/client.py
gspread_pandas/conf.py
gspread_pandas/exceptions.py
gspread_pandas/spread.py
gspread_pandas/util.py
gspread_pandas-3.2.3.dist-info/LICENSE.rst
gspread_pandas-3.2.3.dist-info/METADATA
gspread_pandas-3.2.3.dist-info/WHEEL
gspread_pandas-3.2.3.dist-info/top_level.txt
gspread_pandas-3.2.3.dist-info/RECORD
