Metadata-Version: 2.1
Name: gspread-pandas
Version: 3.2.3
Summary: A package to easily open an instance of a Google spreadsheet and interact with worksheets through Pandas DataFrames.
Home-page: https://github.com/aiguofer/gspread-pandas
Download-URL: https://github.com/aiguofer/gspread-pandas/tarball/v3.2.3
Author: Diego Fernandez
Author-email: aiguo.fernandez@gmail.com
License: BSD
Keywords: gspread pandas google spreadsheets
Classifier: Development Status :: 4 - Beta
Classifier: Intended Audience :: Developers
Classifier: Intended Audience :: Science/Research
Classifier: Programming Language :: Python :: 3
Provides-Extra: dev
License-File: LICENSE.rst
